ucm/__init__.py
ucm/computations.py
ucm/icon.png
ucm/protocols.conf
ucm/protocols/__init__.py
ucm/protocols/protocol_loc_b_factor.py
ucm/protocols/protocol_loc_occupancy.py
scipion_em_ucm-1.0.dist-info/LICENSE
scipion_em_ucm-1.0.dist-info/METADATA
scipion_em_ucm-1.0.dist-info/WHEEL
scipion_em_ucm-1.0.dist-info/entry_points.txt
scipion_em_ucm-1.0.dist-info/top_level.txt
scipion_em_ucm-1.0.dist-info/RECORD
