Metadata-Version: 2.1
Name: scipion-em-ucm
Version: 1.0
Summary: Scipion plugin with map validations
Home-page: https://gitlab.com/jordibc/scipion-em-ucm
Author: Jordi Burguet-Castell, Javier Vargas
Author-email: jburguet@ucm.es, jvargas@fis.ucm.es
License: GPL-3
Keywords: scipion cryoem imageprocessing validation
Platform: UNKNOWN
License-File: LICENSE
Requires-Dist: mrcfile
Requires-Dist: numpy
Requires-Dist: scipion-em
Requires-Dist: scipion-pyworkflow
